homologyviz/__init__.py
homologyviz/app.py
homologyviz/arrow.py
homologyviz/callbacks.py
homologyviz/cli.py
homologyviz/gb_files_manipulation.py
homologyviz/layout.py
homologyviz/logger.py
homologyviz/miscellaneous.py
homologyviz/parameters.py
homologyviz/plotter.py
homologyviz/rectangle_bezier.py
homologyviz/assets/__init__.py
homologyviz/assets/logo.png
homologyviz/assets/shutdown.js
homologyviz/assets/style.css
homologyviz/images/HomologyViz_app.png
homologyviz/images/__init__.py
homologyviz-0.1.33.dist-info/licenses/LICENSE
homologyviz-0.1.33.dist-info/METADATA
homologyviz-0.1.33.dist-info/WHEEL
homologyviz-0.1.33.dist-info/entry_points.txt
homologyviz-0.1.33.dist-info/top_level.txt
homologyviz-0.1.33.dist-info/RECORD
