Metadata-Version: 2.4
Name: homologyviz
Version: 0.1.33
Summary: Create visual representations of BLASTn alignments
Author-email: Ivan Munoz-Gutierrez <ivan.munoz.gutierrez@gmail.com>
Maintainer-email: Ivan Munoz-Gutierrez <ivan.munoz.gutierrez@gmail.com>
License: BSD-3-Clause
Project-URL: Repository, https://github.com/ivanmugu/homologyviz
Project-URL: Homepage, https://github.com/ivanmugu/homologyviz
Keywords: DNA alignments,BLASTn,Graphical BLASTn alignments,easyfig
Classifier: Programming Language :: Python :: 3.11
Classifier: Programming Language :: Python :: 3
Classifier: License :: OSI Approved :: BSD License
Classifier: Intended Audience :: Science/Research
Classifier: Operating System :: OS Independent
Classifier: Topic :: Scientific/Engineering :: Bio-Informatics
Classifier: Framework :: Dash
Classifier: Environment :: Web Environment
Requires-Python: >=3.11
License-File: LICENSE
Requires-Dist: bezier
Requires-Dist: biopython
Requires-Dist: dash
Requires-Dist: dash_ag_grid
Requires-Dist: dash-bootstrap-components
Requires-Dist: dash-iconify
Requires-Dist: dash-mantine_components
Requires-Dist: kaleido
Requires-Dist: matplotlib
Requires-Dist: plotly
Requires-Dist: pandas
Provides-Extra: dev
Requires-Dist: pytest; extra == "dev"
Requires-Dist: pytest-cov; extra == "dev"
Dynamic: license-file
